extvip/__init__.py
extvip/colors.py
extvip/console.py
extvip/legacy.py
extvip/log.py
extvip/unique.py
extvip-0.0.0.941.dist-info/LICENSE
extvip-0.0.0.941.dist-info/METADATA
extvip-0.0.0.941.dist-info/WHEEL
extvip-0.0.0.941.dist-info/top_level.txt
extvip-0.0.0.941.dist-info/RECORD
