Metadata-Version: 2.1
Name: extvip
Version: 0.0.0.941
Summary: Extvip // @antilagvip
Home-page: http://pypi.python.org/pypi/extvip
Author: @antilagvip
Author-email: dev@antilag.dev
License: MIT
Project-URL: Homepage, https://github.com/antilagg/extvip
Project-URL: Suggestions, https://github.com/antilagg/extvip/issues
Classifier: Development Status :: 3 - Alpha
Classifier: Intended Audience :: Developers
Classifier: License :: OSI Approved :: MIT License
Classifier: Natural Language :: English
Classifier: Programming Language :: Python
Classifier: Programming Language :: Python :: 3
Classifier: Programming Language :: Python :: 3.8
Classifier: Programming Language :: Python :: 3.9
Classifier: Programming Language :: Python :: 3.10
Classifier: Programming Language :: Python :: 3.11
Classifier: Topic :: Scientific/Engineering
Classifier: Topic :: Scientific/Engineering :: Information Analysis
Classifier: Topic :: Scientific/Engineering :: Mathematics
Classifier: Topic :: Scientific/Engineering :: Visualization
Classifier: Topic :: Software Development :: Libraries
Classifier: Topic :: Utilities
Requires-Python: ~=3.8
License-File: LICENSE
Requires-Dist: colorama >=0.4.6
Requires-Dist: requests >=2.30.0
